netrun/db/__init__.py
netrun/db/config.py
netrun/db/health.py
netrun/db/pool.py
netrun/db/py.typed
netrun/db/tenant.py
netrun/db/middleware/__init__.py
netrun/db/middleware/fastapi.py
netrun/db/middleware/tenant_context.py
netrun_db_pool/__init__.py
netrun_db_pool/config.py
netrun_db_pool/health.py
netrun_db_pool/pool.py
netrun_db_pool/tenant.py
netrun_db_pool/middleware/__init__.py
netrun_db_pool/middleware/fastapi.py
netrun_db_pool/middleware/tenant_context.py
netrun_db_pool-2.0.0.dist-info/METADATA
netrun_db_pool-2.0.0.dist-info/WHEEL
netrun_db_pool-2.0.0.dist-info/licenses/LICENSE
netrun_db_pool-2.0.0.dist-info/RECORD
