Metadata-Version: 2.4
Name: netrun-db-pool
Version: 2.0.0
Summary: Production-grade async database connection pooling for Netrun Systems services
Project-URL: Homepage, https://netrunsystems.com
Project-URL: Documentation, https://github.com/netrunsystems/netrun-db-pool
Project-URL: Repository, https://github.com/netrunsystems/netrun-db-pool
Project-URL: Issues, https://github.com/netrunsystems/netrun-db-pool/issues
Author-email: Daniel Garza <daniel@netrunsystems.com>
Maintainer-email: Netrun Systems <engineering@netrunsystems.com>
License: MIT
License-File: LICENSE
Keywords: asyncpg,connection-pool,database,fastapi,multi-tenant,namespace,netrun,postgresql,rls,sqlalchemy
Classifier: Development Status :: 5 - Production/Stable
Classifier: Framework :: AsyncIO
Classifier: Framework :: FastAPI
Classifier: Intended Audience :: Developers
Classifier: License :: OSI Approved :: MIT License
Classifier: Programming Language :: Python :: 3
Classifier: Programming Language :: Python :: 3.10
Classifier: Programming Language :: Python :: 3.11
Classifier: Programming Language :: Python :: 3.12
Classifier: Topic :: Database
Classifier: Topic :: Software Development :: Libraries :: Python Modules
Classifier: Typing :: Typed
Requires-Python: >=3.10
Requires-Dist: asyncpg<1.0.0,>=0.29.0
Requires-Dist: netrun-core>=1.0.0
Requires-Dist: pydantic-settings<3.0.0,>=2.0.0
Requires-Dist: pydantic<3.0.0,>=2.0.0
Requires-Dist: sqlalchemy[asyncio]<3.0.0,>=2.0.0
Provides-Extra: dev
Requires-Dist: black>=24.0.0; extra == 'dev'
Requires-Dist: mypy>=1.9.0; extra == 'dev'
Requires-Dist: netrun-logging>=2.0.0; extra == 'dev'
Requires-Dist: pytest-asyncio>=0.23.0; extra == 'dev'
Requires-Dist: pytest-cov>=4.1.0; extra == 'dev'
Requires-Dist: pytest>=8.0.0; extra == 'dev'
Requires-Dist: ruff>=0.3.0; extra == 'dev'
Provides-Extra: fastapi
Requires-Dist: fastapi>=0.110.0; extra == 'fastapi'
Requires-Dist: uvicorn>=0.29.0; extra == 'fastapi'
Provides-Extra: logging
Requires-Dist: netrun-logging>=2.0.0; extra == 'logging'
Provides-Extra: redis
Requires-Dist: redis[asyncio]<6.0.0,>=5.0.0; extra == 'redis'
Provides-Extra: testing
Requires-Dist: aiosqlite>=0.20.0; extra == 'testing'
